python_my_orm.py
python_my_orm-1.0.0.dist-info/WHEEL
python_my_orm-1.0.0.dist-info/METADATA
python_my_orm-1.0.0.dist-info/RECORD
