Metadata-Version: 2.3
Name: python_my_orm
Version: 1.0.0
Summary: Uma ORM simples para facilitar a implementação de SQL com Python
Requires-Python: >=3.11
Requires-Dist: pytest==8.3.2 ; extra == "dev"
Requires-Dist: mysql-connector-python ; extra == "mysql"
Requires-Dist: pg8000 ; extra == "postgres"
Requires-Dist: sqlite3 ; extra == "sqlite"
Provides-Extra: dev
Provides-Extra: mysql
Provides-Extra: postgres
Provides-Extra: sqlite
